pymkpsxiso.cp36-win32.pyd
pymkpsxiso-0.1.6.dist-info/LICENSE
pymkpsxiso-0.1.6.dist-info/METADATA
pymkpsxiso-0.1.6.dist-info/WHEEL
pymkpsxiso-0.1.6.dist-info/top_level.txt
pymkpsxiso-0.1.6.dist-info/RECORD
