Metadata-Version: 2.1
Name: pymkpsxiso
Version: 0.1.6
Summary: Python interface for mkpsxiso.
Home-page: https://github.com/Illidanz/pymkpsxiso
Author: Illidan
License: UNKNOWN
Platform: UNKNOWN
Classifier: Programming Language :: Python :: 3
Classifier: License :: OSI Approved :: MIT License
License-File: LICENSE
